lazystore/__init__.py
lazystore/_lazystore.py
lazystore/py.typed
lazystore-0.1.0.dist-info/LICENSE.txt
lazystore-0.1.0.dist-info/METADATA
lazystore-0.1.0.dist-info/WHEEL
lazystore-0.1.0.dist-info/top_level.txt
lazystore-0.1.0.dist-info/RECORD
