Metadata-Version: 2.1
Name: lazystore
Version: 0.1.0
Summary: Store of values created on demand.
Home-page: https://github.com/guludo/lazystore
License: UNKNOWN
Keywords: lazy
Platform: UNKNOWN
Classifier: Development Status :: 3 - Alpha
Classifier: Intended Audience :: Developers
Classifier: License :: OSI Approved :: Mozilla Public License 2.0 (MPL 2.0)
Classifier: Programming Language :: Python :: 3
License-File: LICENSE.txt
Provides-Extra: dev
Requires-Dist: coverage (~=6.2) ; extra == 'dev'
Requires-Dist: mypy (>=0.931<1) ; extra == 'dev'
Requires-Dist: pytest (~=6.2) ; extra == 'dev'
Requires-Dist: pytest-doctestplus (~=0.11.0) ; extra == 'dev'
